ard_transformer/__init__.py
ard_transformer/runner.py
ard_transformer/transformer.py
ard_transformer/version.py
ard_transformer-0.9.3.dist-info/LICENSE
ard_transformer-0.9.3.dist-info/METADATA
ard_transformer-0.9.3.dist-info/WHEEL
ard_transformer-0.9.3.dist-info/entry_points.txt
ard_transformer-0.9.3.dist-info/top_level.txt
ard_transformer-0.9.3.dist-info/RECORD
